<Entity>

	<InheritTransformComponent>
	</InheritTransformComponent>

	<IKLimbComponent
		length="80" >
	</IKLimbComponent>

	<!-- You've served us well invisible fungus leg sprite, but it's time you retire... -->
	<!--
	<SpriteComponent 
		image_file="mods/Apotheosis/files/enemies_gfx/lukki/lukki_fungus_a_long.png" 
		z_index="1.1"
		alpha="0"
		offset_x="0"
		offset_y="5"
		update_transform="0"
		update_transform_rotation="0" >
	</SpriteComponent>

	<SpriteComponent 
		image_file="mods/Apotheosis/files/enemies_gfx/lukki/lukki_fungus_b_long.png" 
		z_index="1.1"
		alpha="0"
		offset_x="0"
		offset_y="5"
		update_transform="0"
		update_transform_rotation="0" >
	</SpriteComponent>

	<SpriteComponent 
		image_file="mods/Apotheosis/files/enemies_gfx/lukki/lukki_fungus_knee.png" 
		z_index="1.1"
		alpha="0"
		offset_x="4"
		offset_y="4"
		update_transform="0"
		update_transform_rotation="0" >
	</SpriteComponent>
	-->

</Entity>